spbel/__init__.py
spbel/proxy.py
spbel/rapel.py
spbel/reply.py
spbel-0.0.3.data/scripts/spbel
spbel-0.0.3.dist-info/LICENSE
spbel-0.0.3.dist-info/METADATA
spbel-0.0.3.dist-info/WHEEL
spbel-0.0.3.dist-info/top_level.txt
spbel-0.0.3.dist-info/RECORD
