Metadata-Version: 2.1
Name: spbel
Version: 0.0.3
Summary: Sentry Proxy Behind Enemy Line
Home-page: https://github.com/freezmeinster/Prot
Author: Bramandityo Praboowo
Author-email: mulacloud@protonmail.com
License: UNKNOWN
Project-URL: Bug Tracker, https://github.com/freezmeinster/Prot/issues
Platform: UNKNOWN
Classifier: Programming Language :: Python :: 3
Classifier: License :: OSI Approved :: MIT License
Classifier: Operating System :: OS Independent
Requires-Python: >=3.6
License-File: LICENSE
